Workbook

Sheet Facturas
A1: Nº Factura | B1: Fecha | C1: Cliente | D1: Comercial | E1: Servicio | F1: Base imponible | G1: IVA | H1: Total | I1: Vencimiento | J1: Estado | K1: Fecha cobro
A2: F-2025-0001 | B2: 45659 | C2: Clínica Estética Lumen | D2: Javier Climent | E2: Mantenimiento climatización | F2: 869.59 | G2: 182.61 | H2: 1052.2 | I2: 45689 | J2: Cobrada | K2: 45689
A3: F-2025-0002 | B3: 45659 | C3: Clínica Dental Ruzafa | D3: Marcos Ibáñez | E3: Instalación eléctrica | F3: 6272.61 | G3: 1317.25 | H3: 7589.86 | I3: 45689 | J3: Cobrada | K3: 45668
A4: F-2025-0003 | B4: 45659 | C4: Hostal Ciutat Vella | D4: Sara Peris | E4: Mantenimiento climatización | F4: 266.8 | G4: 56.03 | H4: 322.83 | I4: 45689 | J4: Cobrada | K4: 45668
A5: F-2025-0004 | B5: 45659 | C5: Hostal Ciutat Vella | D5: Laura Gómez | E5: Mantenimiento climatización | F5: 725.2 | G5: 152.29 | H5: 877.49 | I5: 45689 | J5: Cobrada | K5: 45668
A6: F-2025-0005 | B6: 45660 | C6: Talleres Mecánicos Ribera | D6: Laura Gómez | E6: Instalación aire acondicionado | F6: 4272.84 | G6: 897.3 | H6: 5170.14 | I6: 45690 | J6: Cobrada | K6: 45678
A7: F-2025-0006 | B7: 45660 | C7: Talleres Mecánicos Ribera | D7: Sara Peris | E7: Instalación aire acondicionado | F7: 6327.91 | G7: 1328.86 | H7: 7656.77 | I7: 45690 | J7: Cobrada | K7: 45683
A8: F-2025-0007 | B8: 45663 | C8: Óptica Visión Clara | D8: Laura Gómez | E8: Fontanería | F8: 1812.9 | G8: 380.71 | H8: 2193.61 | I8: 45693 | J8: Cobrada | K8: 45699
A9: F-2025-0008 | B9: 45663 | C9: Supermercados La Huerta | D9: Laura Gómez | E9: Instalación eléctrica | F9: 4685.79 | G9: 984.02 | H9: 5669.81 | I9: 45693 | J9: Cobrada | K9: 45682
A10: F-2025-0009 | B10: 45663 | C10: Clínica Dental Ruzafa | D10: Laura Gómez | E10: Mantenimiento climatización | F10: 378.62 | G10: 79.51 | H10: 458.13 | I10: 45693 | J10: Cobrada | K10: 45683
A11: F-2025-0010 | B11: 45663 | C11: Hotel Marina Sol | D11: Laura Gómez | E11: Instalación aire acondicionado | F11: 4760.13 | G11: 999.63 | H11: 5759.76 | I11: 45693 | J11: Cobrada | K11: 45668
A12: F-2025-0011 | B12: 45664 | C12: Hotel Marina Sol | D12: Javier Climent | E12: Instalación aire acondicionado | F12: 4328.03 | G12: 908.89 | H12: 5236.92 | I12: 45694 | J12: Cobrada | K12: 45697
A13: F-2025-0012 | B13: 45664 | C13: Hotel Marina Sol | D13: Javier Climent | E13: Mantenimiento climatización | F13: 553.37 | G13: 116.21 | H13: 669.58 | I13: 45694 | J13: Cobrada | K13: 45702
... A125: F-2025-0124 | B125: 45698 | C125: Clínica Fisio Mestalla | D125: Sara Peris | E125: Mantenimiento climatización | F125: 547.26 | G125: 114.92 | H125: 662.18 | I125: 45728 | J125: Cobrada | K125: 45704
A126: F-2025-0125 | B126: 45698 | C126: Clínica Dental Ruzafa | D126: Sara Peris | E126: Revisión eficiencia energética | F126: 1614.41 | G126: 339.03 | H126: 1953.44 | I126: 45728 | J126: Vencida
A127: F-2025-0126 | B127: 45699 | C127: Hotel Marina Sol | D127: Laura Gómez | E127: Mantenimiento climatización | F127: 810.81 | G127: 170.27 | H127: 981.08 | I127: 45729 | J127: Cobrada | K127: 45733
A128: F-2025-0127 | B128: 45699 | C128: Pastelería Dulce Albaida | D128: Laura Gómez | E128: Instalación aire acondicionado | F128: 6566.36 | G128: 1378.94 | H128: 7945.3 | I128: 45729 | J128: Cobrada | K128: 45709
A129: F-2025-0128 | B129: 45699 | C129: Clínica Dental Ruzafa | D129: Laura Gómez | E129: Reforma de local | F129: 36708.25 | G129: 7708.73 | H129: 44416.98 | I129: 45729 | J129: Cobrada | K129: 45718
A130: F-2025-0129 | B130: 45699 | C130: Hotel Playa Gandia | D130: Laura Gómez | E130: Mantenimiento climatización | F130: 925.88 | G130: 194.43 | H130: 1120.31 | I130: 45729 | J130: Cobrada | K130: 45713
A131: F-2025-0130 | B131: 45699 | C131: Panadería Horno de Campanar | D131: Sara Peris | E131: Revisión eficiencia energética | F131: 940.78 | G131: 197.56 | H131: 1138.34 | I131: 45729 | J131: Cobrada | K131: 45738
A132: F-2025-0131 | B132: 45699 | C132: Hotel Marina Sol | D132: Laura Gómez | E132: Mantenimiento climatización | F132: 336.81 | G132: 70.73 | H132: 407.54 | I132: 45729 | J132: Cobrada | K132: 45715
A133: F-2025-0132 | B133: 45700 | C133: Academia Idiomas Albufera | D133: Sara Peris | E133: Fontanería | F133: 2195.46 | G133: 461.05 | H133: 2656.51 | I133: 45730 | J133: Cobrada | K133: 45732
A134: F-2025-0133 | B134: 45700 | C134: Hotel Marina Sol | D134: Laura Gómez | E134: Mantenimiento climatización | F134: 731.05 | G134: 153.52 | H134: 884.57 | I134: 45730 | J134: Cobrada | K134: 45723
A135: F-2025-0134 | B135: 45700 | C135: Hotel Marina Sol | D135: Sara Peris | E135: Instalación aire acondicionado | F135: 4259.39 | G135: 894.47 | H135: 5153.86 | I135: 45730 | J135: Cobrada | K135: 45719
A136: F-2025-0135 | B136: 45700 | C136: Restaurante El Palmar | D136: Sara Peris | E136: Contrato mantenimiento anual | F136: 5932.47 | G136: 1245.82 | H136: 7178.29 | I136: 45730 | J136: Cobrada | K136: 45733
A137: F-2025-0136 | B137: 45700 | C137: Colegio Sant Vicent | D137: Marcos Ibáñez | E137: Reparación urgente | F137: 137.58 | G137: 28.89 | H137: 166.47 | I137: 45730 | J137: Cobrada | K137: 45738
A138: F-2025-0137 | B138: 45700 | C138: Clínica Dental Ruzafa | D138: Marcos Ibáñez | E138: Reparación urgente | F138: 534.08 | G138: 112.16 | H138: 646.24 | I138: 45730 | J138: Cobrada | K138: 45728
... A206: F-2025-0205 | B206: 45720 | C206: Restaurante El Palmar | D206: Marcos Ibáñez | E206: Fontanería | F206: 2009.16 | G206: 421.92 | H206: 2431.08 | I206: 45750 | J206: Cobrada | K206: 45730
A207: F-2025-0206 | B207: 45720 | C207: Colegio Sant Vicent | D207: Sara Peris | E207: Instalación eléctrica | F207: 5119.38 | G207: 1075.07 | H207: 6194.45 | I207: 45750 | J207: Vencida
A208: F-2025-0207 | B208: 45720 | C208: Heladería La Alquería | D208: Javier Climent | E208: Fontanería | F208: 1843.98 | G208: 387.24 | H208: 2231.22 | I208: 45750 | J208: Cobrada | K208: 45751
A209: F-2025-0208 | B209: 45720 | C209: Hotel Marina Sol | D209: Marcos Ibáñez | E209: Fontanería | F209: 545.78 | G209: 114.61 | H209: 660.39 | I209: 45750 | J209: Cobrada | K209: 45752
A210: F-2025-0209 | B210: 45721 | C210: Imprenta Gráficas Turia | D210: Sara Peris | E210: Mantenimiento climatización | F210: 437.41 | G210: 91.86 | H210: 529.27 | I210: 45751 | J210: Cobrada | K210: 45727
A211: F-2025-0210 | B211: 45721 | C211: Óptica Visión Clara | D211: Laura Gómez | E211: Reparación urgente | F211: 717.92 | G211: 150.76 | H211: 868.68 | I211: 45751 | J211: Cobrada | K211: 45758
A212: F-2025-0211 | B212: 45721 | C212: Bodegas Requena Alta | D212: Laura Gómez | E212: Mantenimiento climatización | F212: 554.97 | G212: 116.54 | H212: 671.51 | I212: 45751 | J212: Cobrada | K212: 45727
A213: F-2025-0212 | B213: 45721 | C213: Hotel Marina Sol | D213: Sara Peris | E213: Reparación urgente | F213: 662.55 | G213: 139.14 | H213: 801.69 | I213: 45751 | J213: Cobrada | K213: 45740
A214: F-2025-0213 | B214: 45721 | C214: Asesoría Martí & Asociados | D214: Javier Climent | E214: Instalación placas solares | F214: 22726.18 | G214: 4772.5 | H214: 27498.68 | I214: 45751 | J214: Cobrada | K214: 45733
A215: F-2025-0214 | B215: 45722 | C215: Colegio Sant Vicent | D215: Laura Gómez | E215: Instalación aire acondicionado | F215: 4866.01 | G215: 1021.86 | H215: 5887.87 | I215: 45752 | J215: Cobrada | K215: 45729
A216: F-2025-0215 | B216: 45722 | C216: Colegio Sant Vicent | D216: Marcos Ibáñez | E216: Instalación aire acondicionado | F216: 4747.6 | G216: 997 | H216: 5744.6 | I216: 45752 | J216: Cobrada | K216: 45728
A217: F-2025-0216 | B217: 45722 | C217: Cárnicas del Mediterráneo | D217: Laura Gómez | E217: Reparación urgente | F217: 213.63 | G217: 44.86 | H217: 258.49 | I217: 45752 | J217: Cobrada | K217: 45730
A218: F-2025-0217 | B218: 45722 | C218: Colegio Sant Vicent | D218: Laura Gómez | E218: Instalación placas solares | F218: 10284.53 | G218: 2159.75 | H218: 12444.28 | I218: 45752 | J218: Cobrada | K218: 45753
A219: F-2025-0218 | B219: 45722 | C219: Supermercados La Huerta | D219: Marcos Ibáñez | E219: Contrato mantenimiento anual | F219: 7025.17 | G219: 1475.29 | H219: 8500.46 | I219: 45752 | J219: Cobrada | K219: 45731
... A261: F-2025-0260 | B261: 45733 | C261: Hotel Playa Gandia | D261: Marcos Ibáñez | E261: Reparación urgente | F261: 392.44 | G261: 82.41 | H261: 474.85 | I261: 45763 | J261: Cobrada | K261: 45753
A262: F-2025-0261 | B262: 45733 | C262: Residencia Los Naranjos | D262: Laura Gómez | E262: Instalación aire acondicionado | F262: 7112.3 | G262: 1493.58 | H262: 8605.88 | I262: 45763 | J262: Vencida
A263: F-2025-0262 | B263: 45733 | C263: Escuela Infantil Petits | D263: Marcos Ibáñez | E263: Reparación urgente | F263: 192.67 | G263: 40.46 | H263: 233.13 | I263: 45763 | J263: Cobrada | K263: 45752
A264: F-2025-0263 | B264: 45734 | C264: Hotel Marina Sol | D264: Laura Gómez | E264: Mantenimiento climatización | F264: 252.86 | G264: 53.1 | H264: 305.96 | I264: 45764 | J264: Cobrada | K264: 45758
A265: F-2025-0264 | B265: 45734 | C265: Peluquería Studio Nueve | D265: Javier Climent | E265: Instalación aire acondicionado | F265: 2567.29 | G265: 539.13 | H265: 3106.42 | I265: 45764 | J265: Cobrada | K265: 45769
A266: F-2025-0265 | B266: 45734 | C266: Estudio Arquitectura Cabanyal | D266: Javier Climent | E266: Instalación eléctrica | F266: 4227.27 | G266: 887.73 | H266: 5115 | I266: 45764 | J266: Cobrada | K266: 45745
A267: F-2025-0266 | B267: 45734 | C267: Academia Idiomas Albufera | D267: Javier Climent | E267: Revisión eficiencia energética | F267: 690.63 | G267: 145.03 | H267: 835.66 | I267: 45764 | J267: Cobrada | K267: 45754
A268: F-2025-0267 | B268: 45734 | C268: Supermercados La Huerta | D268: Javier Climent | E268: Mantenimiento climatización | F268: 508.61 | G268: 106.81 | H268: 615.42 | I268: 45764 | J268: Cobrada | K268: 45752
A269: F-2025-0268 | B269: 45734 | C269: Logística Puerto Sur | D269: Javier Climent | E269: Mantenimiento climatización | F269: 202.76 | G269: 42.58 | H269: 245.34 | I269: 45764 | J269: Cobrada | K269: 45745
A270: F-2025-0269 | B270: 45735 | C270: Clínica Dental Ruzafa | D270: Laura Gómez | E270: Mantenimiento climatización | F270: 347.34 | G270: 72.94 | H270: 420.28 | I270: 45765 | J270: Cobrada | K270: 45763
A271: F-2025-0270 | B271: 45735 | C271: Hotel Marina Sol | D271: Laura Gómez | E271: Mantenimiento climatización | F271: 313.48 | G271: 65.83 | H271: 379.31 | I271: 45765 | J271: Cobrada | K271: 45773
A272: F-2025-0271 | B272: 45735 | C272: Hotel Marina Sol | D272: Javier Climent | E272: Revisión eficiencia energética | F272: 728.3 | G272: 152.94 | H272: 881.24 | I272: 45765 | J272: Cobrada | K272: 45756
A273: F-2025-0272 | B273: 45736 | C273: Hotel Marina Sol | D273: Marcos Ibáñez | E273: Revisión eficiencia energética | F273: 1052.47 | G273: 221.02 | H273: 1273.49 | I273: 45766 | J273: Cobrada | K273: 45770
A274: F-2025-0273 | B274: 45736 | C274: Hotel Marina Sol | D274: Marcos Ibáñez | E274: Instalación eléctrica | F274: 5889.06 | G274: 1236.7 | H274: 7125.76 | I274: 45766 | J274: Cobrada | K274: 45763
... A345: F-2025-0344 | B345: 45754 | C345: Logística Puerto Sur | D345: Laura Gómez | E345: Reforma de local | F345: 32731.18 | G345: 6873.55 | H345: 39604.73 | I345: 45784 | J345: Cobrada | K345: 45783
A346: F-2025-0345 | B346: 45754 | C346: Hotel Marina Sol | D346: Marcos Ibáñez | E346: Reforma de local | F346: 36612.89 | G346: 7688.71 | H346: 44301.6 | I346: 45784 | J346: Vencida
A347: F-2025-0346 | B347: 45754 | C347: Farmacia Russafa 24h | D347: Sara Peris | E347: Reforma de local | F347: 29965 | G347: 6292.65 | H347: 36257.65 | I347: 45784 | J347: Cobrada | K347: 45760
A348: F-2025-0347 | B348: 45754 | C348: Supermercados La Huerta | D348: Javier Climent | E348: Reparación urgente | F348: 451.6 | G348: 94.84 | H348: 546.44 | I348: 45784 | J348: Cobrada | K348: 45776
A349: F-2025-0348 | B349: 45754 | C349: Muebles Ebanistas Manises | D349: Marcos Ibáñez | E349: Instalación eléctrica | F349: 5392.59 | G349: 1132.44 | H349: 6525.03 | I349: 45784 | J349: Cobrada | K349: 45767
A350: F-2025-0349 | B350: 45754 | C350: Supermercados La Huerta | D350: Laura Gómez | E350: Mantenimiento climatización | F350: 720.84 | G350: 151.38 | H350: 872.22 | I350: 45784 | J350: Cobrada | K350: 45768
A351: F-2025-0350 | B351: 45754 | C351: Clínica Dental Ruzafa | D351: Marcos Ibáñez | E351: Reparación urgente | F351: 631.13 | G351: 132.54 | H351: 763.67 | I351: 45784 | J351: Cobrada | K351: 45772
A352: F-2025-0351 | B352: 45755 | C352: Hotel Marina Sol | D352: Sara Peris | E352: Mantenimiento climatización | F352: 747.76 | G352: 157.03 | H352: 904.79 | I352: 45785 | J352: Cobrada | K352: 45793
A353: F-2025-0352 | B353: 45755 | C353: Colegio Sant Vicent | D353: Marcos Ibáñez | E353: Fontanería | F353: 846.96 | G353: 177.86 | H353: 1024.82 | I353: 45785 | J353: Cobrada | K353: 45768
A354: F-2025-0353 | B354: 45755 | C354: Logística Puerto Sur | D354: Marcos Ibáñez | E354: Mantenimiento climatización | F354: 262.9 | G354: 55.21 | H354: 318.11 | I354: 45785 | J354: Cobrada | K354: 45792
A355: F-2025-0354 | B355: 45755 | C355: Psicología Espacio Calma | D355: Javier Climent | E355: Revisión eficiencia energética | F355: 1093.35 | G355: 229.6 | H355: 1322.95 | I355: 45785 | J355: Cobrada | K355: 45785
A356: F-2025-0355 | B356: 45755 | C356: Cárnicas del Mediterráneo | D356: Javier Climent | E356: Instalación eléctrica | F356: 6462.82 | G356: 1357.19 | H356: 7820.01 | I356: 45785 | J356: Cobrada | K356: 45764
A357: F-2025-0356 | B357: 45755 | C357: Coworking Ensanche | D357: Laura Gómez | E357: Contrato mantenimiento anual | F357: 5715.66 | G357: 1200.29 | H357: 6915.95 | I357: 45785 | J357: Cobrada | K357: 45783
A358: F-2025-0357 | B358: 45755 | C358: Hostal Ciutat Vella | D358: Marcos Ibáñez | E358: Mantenimiento climatización | F358: 919.46 | G358: 193.09 | H358: 1112.55 | I358: 45785 | J358: Cobrada | K358: 45774
A359: F-2025-0358 | B359: 45755 | C359: Supermercados La Huerta | D359: Javier Climent | E359: Reparación urgente | F359: 542.16 | G359: 113.85 | H359: 656.01 | I359: 45785 | J359: Cobrada | K359: 45791
A360: F-2025-0359 | B360: 45756 | C360: Supermercados La Huerta | D360: Laura Gómez | E360: Instalación eléctrica | F360: 2310.65 | G360: 485.24 | H360: 2795.89 | I360: 45786 | J360: Vencida
A361: F-2025-0360 | B361: 45756 | C361: Talleres Mecánicos Ribera | D361: Sara Peris | E361: Mantenimiento climatización | F361: 645.18 | G361: 135.49 | H361: 780.67 | I361: 45786 | J361: Cobrada | K361: 45762
A362: F-2025-0361 | B362: 45756 | C362: Farmacia Russafa 24h | D362: Javier Climent | E362: Fontanería | F362: 1575.19 | G362: 330.79 | H362: 1905.98 | I362: 45786 | J362: Cobrada | K362: 45778
A363: F-2025-0362 | B363: 45756 | C363: Bodegas Requena Alta | D363: Sara Peris | E363: Fontanería | F363: 370.97 | G363: 77.9 | H363: 448.87 | I363: 45786 | J363: Cobrada | K363: 45779
A364: F-2025-0363 | B364: 45756 | C364: Laboratorio Análisis Nou | D364: Sara Peris | E364: Mantenimiento climatización | F364: 506.14 | G364: 106.29 | H364: 612.43 | I364: 45786 | J364: Cobrada | K364: 45762
A365: F-2025-0364 | B365: 45756 | C365: Academia Idiomas Albufera | D365: Laura Gómez | E365: Reparación urgente | F365: 141.53 | G365: 29.72 | H365: 171.25 | I365: 45786 | J365: Cobrada | K365: 45763
A366: F-2025-0365 | B366: 45756 | C366: Hotel Marina Sol | D366: Javier Climent | E366: Instalación eléctrica | F366: 3202.28 | G366: 672.48 | H366: 3874.76 | I366: 45786 | J366: Cobrada | K366: 45795
A367: F-2025-0366 | B367: 45757 | C367: Centro Comercial Arena Norte | D367: Laura Gómez | E367: Reforma de local | F367: 22360.33 | G367: 4695.67 | H367: 27056 | I367: 45787 | J367: Cobrada | K367: 45781
A368: F-2025-0367 | B368: 45757 | C368: Restaurante El Palmar | D368: Marcos Ibáñez | E368: Mantenimiento climatización | F368: 240.83 | G368: 50.57 | H368: 291.4 | I368: 45787 | J368: Cobrada | K368: 45781
A369: F-2025-0368 | B369: 45757 | C369: Supermercados La Huerta | D369: Laura Gómez | E369: Contrato mantenimiento anual | F369: 4692.08 | G369: 985.34 | H369: 5677.42 | I369: 45787 | J369: Cobrada | K369: 45785
A370: F-2025-0369 | B370: 45757 | C370: Academia Idiomas Albufera | D370: Javier Climent | E370: Contrato mantenimiento anual | F370: 3832.29 | G370: 804.78 | H370: 4637.07 | I370: 45787 | J370: Cobrada | K370: 45795
A371: F-2025-0370 | B371: 45757 | C371: Concesionario Motor Levante | D371: Marcos Ibáñez | E371: Fontanería | F371: 1847.12 | G371: 387.9 | H371: 2235.02 | I371: 45787 | J371: Cobrada | K371: 45766
A372: F-2025-0371 | B372: 45758 | C372: Tienda Deportes Cumbre | D372: Sara Peris | E372: Instalación eléctrica | F372: 3994.94 | G372: 838.94 | H372: 4833.88 | I372: 45788 | J372: Cobrada | K372: 45782
... A410: F-2025-0409 | B410: 45769 | C410: Club de Tenis Valterna | D410: Sara Peris | E410: Revisión eficiencia energética | F410: 806.4 | G410: 169.34 | H410: 975.74 | I410: 45799 | J410: Cobrada | K410: 45784
A411: F-2025-0410 | B411: 45769 | C411: Colegio Sant Vicent | D411: Laura Gómez | E411: Instalación aire acondicionado | F411: 8421.46 | G411: 1768.51 | H411: 10189.97 | I411: 45799 | J411: Vencida
A412: F-2025-0411 | B412: 45770 | C412: Colegio Sant Vicent | D412: Sara Peris | E412: Fontanería | F412: 1161.79 | G412: 243.98 | H412: 1405.77 | I412: 45800 | J412: Cobrada | K412: 45787
A413: F-2025-0412 | B413: 45770 | C413: Centro Comercial Arena Norte | D413: Laura Gómez | E413: Reparación urgente | F413: 762.2 | G413: 160.06 | H413: 922.26 | I413: 45800 | J413: Cobrada | K413: 45803
A414: F-2025-0413 | B414: 45770 | C414: Clínica Dental Ruzafa | D414: Marcos Ibáñez | E414: Revisión eficiencia energética | F414: 927.53 | G414: 194.78 | H414: 1122.31 | I414: 45800 | J414: Cobrada | K414: 45786
A415: F-2025-0414 | B415: 45770 | C415: Asesoría Martí & Asociados | D415: Sara Peris | E415: Contrato mantenimiento anual | F415: 5346.21 | G415: 1122.7 | H415: 6468.91 | I415: 45800 | J415: Cobrada | K415: 45797
A416: F-2025-0415 | B416: 45770 | C416: Almacenes Frigoríficos Cullera | D416: Marcos Ibáñez | E416: Instalación aire acondicionado | F416: 8721.61 | G416: 1831.54 | H416: 10553.15 | I416: 45800 | J416: Cobrada | K416: 45804
A417: F-2025-0416 | B417: 45770 | C417: Hotel Marina Sol | D417: Laura Gómez | E417: Instalación eléctrica | F417: 1869.26 | G417: 392.54 | H417: 2261.8 | I417: 45800 | J417: Cobrada | K417: 45803
A418: F-2025-0417 | B418: 45771 | C418: Colegio Sant Vicent | D418: Laura Gómez | E418: Instalación eléctrica | F418: 4003.2 | G418: 840.67 | H418: 4843.87 | I418: 45801 | J418: Cobrada | K418: 45784
A419: F-2025-0418 | B419: 45771 | C419: Hotel Marina Sol | D419: Sara Peris | E419: Instalación eléctrica | F419: 1398.59 | G419: 293.7 | H419: 1692.29 | I419: 45801 | J419: Cobrada | K419: 45810
A420: F-2025-0419 | B420: 45771 | C420: Residencia Los Naranjos | D420: Javier Climent | E420: Mantenimiento climatización | F420: 515.48 | G420: 108.25 | H420: 623.73 | I420: 45801 | J420: Cobrada | K420: 45789
A421: F-2025-0420 | B421: 45771 | C421: Clínica Dental Ruzafa | D421: Sara Peris | E421: Mantenimiento climatización | F421: 531.07 | G421: 111.52 | H421: 642.59 | I421: 45801 | J421: Cobrada | K421: 45802
A422: F-2025-0421 | B422: 45771 | C422: Imprenta Gráficas Turia | D422: Laura Gómez | E422: Contrato mantenimiento anual | F422: 6277.21 | G422: 1318.21 | H422: 7595.42 | I422: 45801 | J422: Cobrada | K422: 45802
A423: F-2025-0422 | B423: 45771 | C423: Restaurante El Palmar | D423: Marcos Ibáñez | E423: Mantenimiento climatización | F423: 734.52 | G423: 154.25 | H423: 888.77 | I423: 45801 | J423: Cobrada | K423: 45809
... A549: F-2025-0548 | B549: 45800 | C549: Clínica Dental Ruzafa | D549: Laura Gómez | E549: Instalación aire acondicionado | F549: 2972.9 | G549: 624.31 | H549: 3597.21 | I549: 45830 | J549: Cobrada | K549: 45817
A550: F-2025-0549 | B550: 45800 | C550: Spa Termal Bétera | D550: Marcos Ibáñez | E550: Mantenimiento climatización | F550: 437.41 | G550: 91.86 | H550: 529.27 | I550: 45830 | J550: Vencida
A551: F-2025-0550 | B551: 45800 | C551: Restaurante El Palmar | D551: Marcos Ibáñez | E551: Mantenimiento climatización | F551: 631.42 | G551: 132.6 | H551: 764.02 | I551: 45830 | J551: Cobrada | K551: 45815
...

Sheet Clientes
A1: Cliente | B1: CIF | C1: Sector | D1: Población | E1: Cliente desde
A2: Hotel Marina Sol | B2: B37876771 | C2: Hostelería | D2: Valencia | E2: 42714
A3: Clínica Dental Ruzafa | B3: B44077846 | C3: Salud | D3: Valencia | E3: 42863
A4: Colegio Sant Vicent | B4: B86654701 | C4: Educación | D4: Paterna | E4: 43285
A5: Supermercados La Huerta | B5: B70753282 | C5: Retail | D5: Torrent | E5: 43720
A6: Estudio Arquitectura Cabanyal | B6: B35627726 | C6: Servicios profesionales | D6: Valencia | E6: 43929
A7: Residencia Los Naranjos | B7: B81474515 | C7: Salud | D7: Alzira | E7: 44556
A8: Gimnasio Turia Fit | B8: B31308772 | C8: Deporte | D8: Valencia | E8: 44745
A9: Logística Puerto Sur | B9: B80293288 | C9: Logística | D9: Sagunto | E9: 44953
A10: Restaurante El Palmar | B10: B58441829 | C10: Hostelería | D10: Valencia | E10: 45342
A11: Centro Médico Benimaclet | B11: B56235501 | C11: Salud | D11: Valencia | E11: 42524
A12: Academia Idiomas Albufera | B12: B44420644 | C12: Educación | D12: Catarroja | E12: 43095
A13: Talleres Mecánicos Ribera | B13: B17302352 | C13: Industria | D13: Alzira | E13: 43300
... A51: Librería Papel y Tinta | B51: B35935441 | C51: Retail | D51: Valencia | E51: 44181

Sheet Gastos
A1: Fecha | B1: Proveedor | C1: Categoría | D1: Concepto | E1: Importe
A2: 45659 | B2: Climatización Distribución SL | C2: Material | D2: Material climatización | E2: 6429.75
A3: 45659 | B3: Telefonía Empresa Total | C3: Oficina | D3: Oficina telefonía | E3: 230.4
A4: 45659 | B4: Papelería Oficina Express | C4: Oficina | D4: Oficina papelería | E4: 314.06
A5: 45659 | B5: Papelería Oficina Express | C5: Oficina | D5: Oficina papelería | E5: 330.16
A6: 45659 | B6: Papelería Oficina Express | C6: Oficina | D6: Oficina papelería | E6: 204.44
A7: 45660 | B7: Climatización Distribución SL | C7: Material | D7: Material climatización | E7: 4206.86
A8: 45660 | B8: Papelería Oficina Express | C8: Oficina | D8: Oficina papelería | E8: 287.82
A9: 45660 | B9: Software Gestión Obras | C9: Software | D9: Software software | E9: 79.49
A10: 45660 | B10: Gasolinera Autovía Norte | C10: Vehículos | D10: Vehículos gasolinera | E10: 415.59
A11: 45663 | B11: Gestoría Laboral Centro | C11: Servicios externos | D11: Servicios externos gestoría | E11: 227.28
A12: 45663 | B12: Subcontratas Montajes Ribera | C12: Subcontratas | D12: Subcontratas subcontratas | E12: 2945.04
A13: 45663 | B13: Renting Furgonetas Plus | C13: Vehículos | D13: Vehículos renting | E13: 931.27
... A2841: 46314 | B2841: Papelería Oficina Express | C2841: Oficina | D2841: Oficina papelería | E2841: 103.64

Sheet Resumen
A1: Mes | B1: Facturado (base) | C1: Gastos | D1: Margen | E1: Pendiente de cobro
A2: 45658 | B2: =SUMIFS(Facturas!$F$2:$F$2632,Facturas!$B$2:$B$2632,">="&A2,Facturas!$B$2:$B$2632,"<"&EDATE(A2,1)) -> 405643.09 | C2: =SUMIFS(Gastos!$E$2:$E$2841,Gastos!$A$2:$A$2841,">="&A2,Gastos!$A$2:$A$2841,"<"&EDATE(A2,1)) -> 208092.11 | D2: =IFERROR(B2-C2,0) -> 197550.98 | E2: 0
A3: 45689 | B3: =SUMIFS(Facturas!$F$2:$F$2632,Facturas!$B$2:$B$2632,">="&A3,Facturas!$B$2:$B$2632,"<"&EDATE(A3,1)) -> 370515.51 | C3: =SUMIFS(Gastos!$E$2:$E$2841,Gastos!$A$2:$A$2841,">="&A3,Gastos!$A$2:$A$2841,"<"&EDATE(A3,1)) -> 214140.52 | D3: =IFERROR(B3-C3,0) -> 156374.99 | E3: =SUMIFS(Facturas!$H$2:$H$2632,Facturas!$B$2:$B$2632,">="&A3,Facturas!$B$2:$B$2632,"<"&EDATE(A3,1),Facturas!$J$2:$J$2632,"<>Cobrada") -> 1953.44
A4: 45717 | B4: =SUMIFS(Facturas!$F$2:$F$2632,Facturas!$B$2:$B$2632,">="&A4,Facturas!$B$2:$B$2632,"<"&EDATE(A4,1)) -> 347842.25 | C4: =SUMIFS(Gastos!$E$2:$E$2841,Gastos!$A$2:$A$2841,">="&A4,Gastos!$A$2:$A$2841,"<"&EDATE(A4,1)) -> 221084.66 | D4: =IFERROR(B4-C4,0) -> 126757.59 | E4: =SUMIFS(Facturas!$H$2:$H$2632,Facturas!$B$2:$B$2632,">="&A4,Facturas!$B$2:$B$2632,"<"&EDATE(A4,1),Facturas!$J$2:$J$2632,"<>Cobrada") -> 14800.33
A5: 45748 | B5: =SUMIFS(Facturas!$F$2:$F$2632,Facturas!$B$2:$B$2632,">="&A5,Facturas!$B$2:$B$2632,"<"&EDATE(A5,1)) -> 480562.98 | C5: =SUMIFS(Gastos!$E$2:$E$2841,Gastos!$A$2:$A$2841,">="&A5,Gastos!$A$2:$A$2841,"<"&EDATE(A5,1)) -> 248536.79 | D5: =IFERROR(B5-C5,0) -> 232026.19 | E5: =SUMIFS(Facturas!$H$2:$H$2632,Facturas!$B$2:$B$2632,">="&A5,Facturas!$B$2:$B$2632,"<"&EDATE(A5,1),Facturas!$J$2:$J$2632,"<>Cobrada") -> 57287.46
A6: 45778 | B6: =SUMIFS(Facturas!$F$2:$F$2632,Facturas!$B$2:$B$2632,">="&A6,Facturas!$B$2:$B$2632,"<"&EDATE(A6,1)) -> 523389.07 | C6: =SUMIFS(Gastos!$E$2:$E$2841,Gastos!$A$2:$A$2841,">="&A6,Gastos!$A$2:$A$2841,"<"&EDATE(A6,1)) -> 272884.67 | D6: =IFERROR(B6-C6,0) -> 250504.4 | E6: =SUMIFS(Facturas!$H$2:$H$2632,Facturas!$B$2:$B$2632,">="&A6,Facturas!$B$2:$B$2632,"<"&EDATE(A6,1),Facturas!$J$2:$J$2632,"<>Cobrada") -> 529.27
A7: 45809 | B7: =SUMIFS(Facturas!$F$2:$F$2632,Facturas!$B$2:$B$2632,">="&A7,Facturas!$B$2:$B$2632,"<"&EDATE(A7,1)) -> 511595 | C7: =SUMIFS(Gastos!$E$2:$E$2841,Gastos!$A$2:$A$2841,">="&A7,Gastos!$A$2:$A$2841,"<"&EDATE(A7,1)) -> 315519.66 | D7: =IFERROR(B7-C7,0) -> 196075.34 | E7: 0
A8: 45839 | B8: =SUMIFS(Facturas!$F$2:$F$2632,Facturas!$B$2:$B$2632,">="&A8,Facturas!$B$2:$B$2632,"<"&EDATE(A8,1)) -> 322483.38 | C8: =SUMIFS(Gastos!$E$2:$E$2841,Gastos!$A$2:$A$2841,">="&A8,Gastos!$A$2:$A$2841,"<"&EDATE(A8,1)) -> 285198.81 | D8: =IFERROR(B8-C8,0) -> 37284.57 | E8: =SUMIFS(Facturas!$H$2:$H$2632,Facturas!$B$2:$B$2632,">="&A8,Facturas!$B$2:$B$2632,"<"&EDATE(A8,1),Facturas!$J$2:$J$2632,"<>Cobrada") -> 9306.45
A9: 45870 | B9: =SUMIFS(Facturas!$F$2:$F$2632,Facturas!$B$2:$B$2632,">="&A9,Facturas!$B$2:$B$2632,"<"&EDATE(A9,1)) -> 146360.24 | C9: =SUMIFS(Gastos!$E$2:$E$2841,Gastos!$A$2:$A$2841,">="&A9,Gastos!$A$2:$A$2841,"<"&EDATE(A9,1)) -> 126778.37 | D9: =IFERROR(B9-C9,0) -> 19581.87 | E9: =SUMIFS(Facturas!$H$2:$H$2632,Facturas!$B$2:$B$2632,">="&A9,Facturas!$B$2:$B$2632,"<"&EDATE(A9,1),Facturas!$J$2:$J$2632,"<>Cobrada") -> 7455.25
A10: 45901 | B10: =SUMIFS(Facturas!$F$2:$F$2632,Facturas!$B$2:$B$2632,">="&A10,Facturas!$B$2:$B$2632,"<"&EDATE(A10,1)) -> 493229.07 | C10: =SUMIFS(Gastos!$E$2:$E$2841,Gastos!$A$2:$A$2841,">="&A10,Gastos!$A$2:$A$2841,"<"&EDATE(A10,1)) -> 306806.17 | D10: =IFERROR(B10-C10,0) -> 186422.9 | E10: 0
A11: 45931 | B11: =SUMIFS(Facturas!$F$2:$F$2632,Facturas!$B$2:$B$2632,">="&A11,Facturas!$B$2:$B$2632,"<"&EDATE(A11,1)) -> 477255.27 | C11: =SUMIFS(Gastos!$E$2:$E$2841,Gastos!$A$2:$A$2841,">="&A11,Gastos!$A$2:$A$2841,"<"&EDATE(A11,1)) -> 318491.36 | D11: =IFERROR(B11-C11,0) -> 158763.91 | E11: =SUMIFS(Facturas!$H$2:$H$2632,Facturas!$B$2:$B$2632,">="&A11,Facturas!$B$2:$B$2632,"<"&EDATE(A11,1),Facturas!$J$2:$J$2632,"<>Cobrada") -> 6600.74
A12: 45962 | B12: =SUMIFS(Facturas!$F$2:$F$2632,Facturas!$B$2:$B$2632,">="&A12,Facturas!$B$2:$B$2632,"<"&EDATE(A12,1)) -> 349451.59 | C12: =SUMIFS(Gastos!$E$2:$E$2841,Gastos!$A$2:$A$2841,">="&A12,Gastos!$A$2:$A$2841,"<"&EDATE(A12,1)) -> 223137.02 | D12: =IFERROR(B12-C12,0) -> 126314.57 | E12: =SUMIFS(Facturas!$H$2:$H$2632,Facturas!$B$2:$B$2632,">="&A12,Facturas!$B$2:$B$2632,"<"&EDATE(A12,1),Facturas!$J$2:$J$2632,"<>Cobrada") -> 3963.51
A13: 45992 | B13: =SUMIFS(Facturas!$F$2:$F$2632,Facturas!$B$2:$B$2632,">="&A13,Facturas!$B$2:$B$2632,"<"&EDATE(A13,1)) -> 380835.95 | C13: =SUMIFS(Gastos!$E$2:$E$2841,Gastos!$A$2:$A$2841,">="&A13,Gastos!$A$2:$A$2841,"<"&EDATE(A13,1)) -> 224637.42 | D13: =IFERROR(B13-C13,0) -> 156198.53 | E13: 0
A14: 46023 | B14: =SUMIFS(Facturas!$F$2:$F$2632,Facturas!$B$2:$B$2632,">="&A14,Facturas!$B$2:$B$2632,"<"&EDATE(A14,1)) -> 274109.52 | C14: =SUMIFS(Gastos!$E$2:$E$2841,Gastos!$A$2:$A$2841,">="&A14,Gastos!$A$2:$A$2841,"<"&EDATE(A14,1)) -> 250111.85 | D14: =IFERROR(B14-C14,0) -> 23997.67 | E14: =SUMIFS(Facturas!$H$2:$H$2632,Facturas!$B$2:$B$2632,">="&A14,Facturas!$B$2:$B$2632,"<"&EDATE(A14,1),Facturas!$J$2:$J$2632,"<>Cobrada") -> 10144.36
A15: 46054 | B15: =SUMIFS(Facturas!$F$2:$F$2632,Facturas!$B$2:$B$2632,">="&A15,Facturas!$B$2:$B$2632,"<"&EDATE(A15,1)) -> 379532.64 | C15: =SUMIFS(Gastos!$E$2:$E$2841,Gastos!$A$2:$A$2841,">="&A15,Gastos!$A$2:$A$2841,"<"&EDATE(A15,1)) -> 223996.72 | D15: =IFERROR(B15-C15,0) -> 155535.92 | E15: =SUMIFS(Facturas!$H$2:$H$2632,Facturas!$B$2:$B$2632,">="&A15,Facturas!$B$2:$B$2632,"<"&EDATE(A15,1),Facturas!$J$2:$J$2632,"<>Cobrada") -> 812.89
A16: 46082 | B16: =SUMIFS(Facturas!$F$2:$F$2632,Facturas!$B$2:$B$2632,">="&A16,Facturas!$B$2:$B$2632,"<"&EDATE(A16,1)) -> 450018.98 | C16: =SUMIFS(Gastos!$E$2:$E$2841,Gastos!$A$2:$A$2841,">="&A16,Gastos!$A$2:$A$2841,"<"&EDATE(A16,1)) -> 257675.08 | D16: =IFERROR(B16-C16,0) -> 192343.9 | E16: 0
A17: 46113 | B17: =SUMIFS(Facturas!$F$2:$F$2632,Facturas!$B$2:$B$2632,">="&A17,Facturas!$B$2:$B$2632,"<"&EDATE(A17,1)) -> 486434.14 | C17: =SUMIFS(Gastos!$E$2:$E$2841,Gastos!$A$2:$A$2841,">="&A17,Gastos!$A$2:$A$2841,"<"&EDATE(A17,1)) -> 289261.25 | D17: =IFERROR(B17-C17,0) -> 197172.89 | E17: =SUMIFS(Facturas!$H$2:$H$2632,Facturas!$B$2:$B$2632,">="&A17,Facturas!$B$2:$B$2632,"<"&EDATE(A17,1),Facturas!$J$2:$J$2632,"<>Cobrada") -> 1739.98
A18: 46143 | B18: =SUMIFS(Facturas!$F$2:$F$2632,Facturas!$B$2:$B$2632,">="&A18,Facturas!$B$2:$B$2632,"<"&EDATE(A18,1)) -> 529218.48 | C18: =SUMIFS(Gastos!$E$2:$E$2841,Gastos!$A$2:$A$2841,">="&A18,Gastos!$A$2:$A$2841,"<"&EDATE(A18,1)) -> 270251.91 | D18: =IFERROR(B18-C18,0) -> 258966.57 | E18: 0
A19: 46174 | B19: =SUMIFS(Facturas!$F$2:$F$2632,Facturas!$B$2:$B$2632,">="&A19,Facturas!$B$2:$B$2632,"<"&EDATE(A19,1)) -> 591403.85 | C19: =SUMIFS(Gastos!$E$2:$E$2841,Gastos!$A$2:$A$2841,">="&A19,Gastos!$A$2:$A$2841,"<"&EDATE(A19,1)) -> 341286.74 | D19: =IFERROR(B19-C19,0) -> 250117.11 | E19: 0
A20: 46204 | B20: =SUMIFS(Facturas!$F$2:$F$2632,Facturas!$B$2:$B$2632,">="&A20,Facturas!$B$2:$B$2632,"<"&EDATE(A20,1)) -> 452865.79 | C20: =SUMIFS(Gastos!$E$2:$E$2841,Gastos!$A$2:$A$2841,">="&A20,Gastos!$A$2:$A$2841,"<"&EDATE(A20,1)) -> 352900.27 | D20: =IFERROR(B20-C20,0) -> 99965.52 | E20: =SUMIFS(Facturas!$H$2:$H$2632,Facturas!$B$2:$B$2632,">="&A20,Facturas!$B$2:$B$2632,"<"&EDATE(A20,1),Facturas!$J$2:$J$2632,"<>Cobrada") -> 436.94
A21: 46235 | B21: =SUMIFS(Facturas!$F$2:$F$2632,Facturas!$B$2:$B$2632,">="&A21,Facturas!$B$2:$B$2632,"<"&EDATE(A21,1)) -> 228680.71 | C21: =SUMIFS(Gastos!$E$2:$E$2841,Gastos!$A$2:$A$2841,">="&A21,Gastos!$A$2:$A$2841,"<"&EDATE(A21,1)) -> 109418.12 | D21: =IFERROR(B21-C21,0) -> 119262.59 | E21: =SUMIFS(Facturas!$H$2:$H$2632,Facturas!$B$2:$B$2632,">="&A21,Facturas!$B$2:$B$2632,"<"&EDATE(A21,1),Facturas!$J$2:$J$2632,"<>Cobrada") -> 32025.67
A22: 46266 | B22: =SUMIFS(Facturas!$F$2:$F$2632,Facturas!$B$2:$B$2632,">="&A22,Facturas!$B$2:$B$2632,"<"&EDATE(A22,1)) -> 601799.49 | C22: =SUMIFS(Gastos!$E$2:$E$2841,Gastos!$A$2:$A$2841,">="&A22,Gastos!$A$2:$A$2841,"<"&EDATE(A22,1)) -> 229884.92 | D22: =IFERROR(B22-C22,0) -> 371914.57 | E22: =SUMIFS(Facturas!$H$2:$H$2632,Facturas!$B$2:$B$2632,">="&A22,Facturas!$B$2:$B$2632,"<"&EDATE(A22,1),Facturas!$J$2:$J$2632,"<>Cobrada") -> 218490.28
A23: 46296 | B23: =SUMIFS(Facturas!$F$2:$F$2632,Facturas!$B$2:$B$2632,">="&A23,Facturas!$B$2:$B$2632,"<"&EDATE(A23,1)) -> 236480.12 | C23: =SUMIFS(Gastos!$E$2:$E$2841,Gastos!$A$2:$A$2841,">="&A23,Gastos!$A$2:$A$2841,"<"&EDATE(A23,1)) -> 196430.64 | D23: =IFERROR(B23-C23,0) -> 40049.48 | E23: =SUMIFS(Facturas!$H$2:$H$2632,Facturas!$B$2:$B$2632,">="&A23,Facturas!$B$2:$B$2632,"<"&EDATE(A23,1),Facturas!$J$2:$J$2632,"<>Cobrada") -> 161772.27
